{"version": 0.6, "generator": "Overpass API 0.7.62.11 87bfad18", "osm3s": {"timestamp_osm_base": "2026-04-29T12:56:15Z", "copyright": "The data included in this document is from www.openstreetmap.org. The data is made available under ODbL."}, "elements": [{"type": "node", "id": 5102617270, "lat": 41.254385, "lon": 32.6746944}, {"type": "node", "id": 5102617271, "lat": 41.2536081, "lon": 32.6751828}, {"type": "node", "id": 5102617272, "lat": 41.2538475, "lon": 32.6755863}, {"type": "node", "id": 5102617273, "lat": 41.2542732, "lon": 32.6760924}, {"type": "node", "id": 5102617274, "lat": 41.2547575, "lon": 32.6755297}, {"type": "node", "id": 5102617275, "lat": 41.2544994, "lon": 32.6751934}, {"type": "node", "id": 5102617276, "lat": 41.2544568, "lon": 32.6749988}, {"type": "node", "id": 5102617277, "lat": 41.2545127, "lon": 32.6748678}, {"type": "way", "id": 524316961, "nodes": [5102617270, 5102617271, 5102617272, 5102617273, 5102617274, 5102617275, 5102617276, 5102617277, 5102617270], "tags": {"amenity": "university", "name": "Safranbolu Meslek Y\u00fcksekokulu"}}]}